dassana/__init__.py
dassana/api.py
dassana/common.py
dassana/dassana_env.py
dassana/dassana_exception.py
dassana/dassana_logging.py
dassana/dassana_publisher.py
dassana/dassana_publisher_nats.py
dassana-0.11.28.dist-info/METADATA
dassana-0.11.28.dist-info/WHEEL
dassana-0.11.28.dist-info/top_level.txt
dassana-0.11.28.dist-info/RECORD
