Metadata-Version: 2.1
Name: dassana
Version: 0.11.28
Summary: Dassana common data ingestion utilities
Home-page: https://github.com/dassana-io/dassana-python
Author: Dassana
Author-email: support@dassana.io
License: MIT
Requires-Dist: certifi
Requires-Dist: requests
Requires-Dist: urllib3
Requires-Dist: google-cloud-pubsub
Requires-Dist: google-cloud-storage
Requires-Dist: boto3
Requires-Dist: ujson
Requires-Dist: tenacity
Requires-Dist: nats-py
